cmakedbg/__init__.py
cmakedbg/__main__.py
cmakedbg/debugger.py
cmakedbg-0.1.1.dist-info/LICENSE
cmakedbg-0.1.1.dist-info/METADATA
cmakedbg-0.1.1.dist-info/WHEEL
cmakedbg-0.1.1.dist-info/entry_points.txt
cmakedbg-0.1.1.dist-info/RECORD
