Metadata-Version: 2.3
Name: cmakedbg
Version: 0.1.1
Summary: a cmake debugger like gdb. Needs cmake >=3.27
License: AGPL
Keywords: cmake,debugger,cli,debug
Author: subil
Author-email: subil@secondspass.org
Requires-Python: >=3.10
Classifier: Development Status :: 3 - Alpha
Classifier: Intended Audience :: Developers
Classifier: Environment :: Console
Classifier: License :: OSI Approved :: GNU Affero General Public License v3
Classifier: Operating System :: POSIX
Classifier: Programming Language :: Python :: 3.10
Classifier: Programming Language :: Python :: 3.11
Classifier: Programming Language :: Python :: 3.12
Classifier: Programming Language :: Python :: 3.13
Classifier: Programming Language :: Python :: 3.14
Classifier: Programming Language :: Python :: 3.15
Classifier: Topic :: Software Development :: Debuggers
Project-URL: Homepage, https://github.com/secondspass/cmakedbg
